pushinpay/__init__.py
pushinpay/errors.py
pushinpay/pix/__init__.py
pushinpay/pix/responses/__init__.py
pushinpay/pix/responses/qrcode.py
pushinpay-0.3.0.dist-info/licenses/LICENSE
pushinpay-0.3.0.dist-info/METADATA
pushinpay-0.3.0.dist-info/WHEEL
pushinpay-0.3.0.dist-info/top_level.txt
pushinpay-0.3.0.dist-info/RECORD
